Metadata-Version: 2.1
Name: numerix77
Version: 2.0.0
Summary: A simple Python library for basic mathematical operations
Home-page: 
License: MIT
